banglish_dictionary/__init__.py
banglish_dictionary/dictionary_data.json
banglish_dictionary/tui.py
banglish_dictionary_tui-1.0.1.dist-info/METADATA
banglish_dictionary_tui-1.0.1.dist-info/WHEEL
banglish_dictionary_tui-1.0.1.dist-info/entry_points.txt
banglish_dictionary_tui-1.0.1.dist-info/top_level.txt
banglish_dictionary_tui-1.0.1.dist-info/RECORD
