Metadata-Version: 2.4
Name: banglish-dictionary-tui
Version: 1.0.1
Summary: A TUI-based dictionary for Banglish to English translations.
Classifier: Programming Language :: Python :: 3
Classifier: License :: OSI Approved :: MIT License
Classifier: Operating System :: OS Independent
Requires-Python: >=3.8
Requires-Dist: textual
Requires-Dist: rich
